[
    {
        "id": 1,
        "title": "Smart Contract Auditor (Solidity)",
        "company": "SecureChain DAO",
        "location": "Remote, Global",
        "rate": "$100 - $150/hour",
        "type": "Fixed Project",
        "logoUrl": "https://upload.wikimedia.org/wikipedia/commons/thumb/1/12/Algorand_logo.svg/1024px-Algorand_logo.svg.png",
        "isFeatured": true
    },
    {
        "id": 2,
        "title": "DeFi Portfolio Analyst",
        "company": "Data Insights Co.",
        "location": "Zurich, Switzerland",
        "rate": "$6000 - $8000 (Fixed Price)",
        "type": "Fixed Project",
        "logoUrl": "https://static.vecteezy.com/system/resources/previews/016/512/035/original/finance-advisor-logo-design-template-vector.jpg",
        "isFeatured": true
    },
    {
        "id": 3,
        "title": "Ecosystem Technical Writer",
        "company": "EON Labs",
        "location": "Singapore, Asia",
        "rate": "$50/hour",
        "type": "Hourly Contract",
        "logoUrl": "https://upload.wikimedia.org/wikipedia/commons/e/e0/Ethereum_logo_2023.svg",
        "isFeatured": false
    },
    {
        "id": 4,
        "title": "Rust Developer (Polkadot SDK)",
        "company": "Web3 Builders",
        "location": "London, UK",
        "rate": "$70 - $110/hour",
        "type": "Hourly Contract",
        "logoUrl": "https://upload.wikimedia.org/wikipedia/commons/thumb/d/d4/Google_logo_2020.svg/2048px-Google_logo_2020.svg.png",
        "isFeatured": false
    },
    {
        "id": 5,
        "title": "Discord Community Moderator",
        "company": "DAO Governance",
        "location": "Berlin, Germany",
        "rate": "$1500 - $2500 (Monthly Retainer)",
        "type": "Retainer",
        "logoUrl": "https://upload.wikimedia.org/wikipedia/commons/4/4c/Discord_logo.svg",
        "isFeatured": false
    },
    {
        "id": 6,
        "title": "Next.js Frontend DApp Designer",
        "company": "Frontier UX",
        "location": "Amsterdam, Netherlands",
        "rate": "$45 - $80/hour",
        "type": "Part Time",
        "logoUrl": "https://www.vectorlogo.zone/logos/nextjs/nextjs-icon.svg",
        "isFeatured": false
    },
    {
        "id": 7,
        "title": "Marketing Campaign Manager",
        "company": "Nexus Solutions",
        "location": "Toronto, ON, Canada",
        "rate": "$3000 (Fixed Budget)",
        "type": "Fixed Project",
        "logoUrl": "https://www.vectorlogo.zone/logos/nike/nike-icon.svg",
        "isFeatured": false
    },
    {
        "id": 8,
        "title": "Agile Project Coordinator",
        "company": "Trello Experts",
        "location": "Chicago, IL, United States",
        "rate": "$50 - $90/hour",
        "type": "Part Time",
        "logoUrl": "https://upload.wikimedia.org/wikipedia/en/thumb/d/d4/Trello_logo.svg/1280px-Trello_logo.svg.png",
        "isFeatured": true
    },
    {
        "id": 9,
        "title": "UX Consultant (1-Hour Session)",
        "company": "UX Strategy Hub",
        "location": "Remote, Global",
        "rate": "$150 (Per Session)",
        "type": "Consultation",
        "logoUrl": "https://upload.wikimedia.org/wikipedia/commons/thumb/f/f7/React.js_logo.svg/1024px-React.js_logo.svg.png",
        "isFeatured": false
    }
]
